langtest/__init__.py
langtest/consistency/__init__.py
langtest/fairness/__init__.py
langtest/integrity/__init__.py
langtest/performance/__init__.py
langtest/performance/rouge.py
langtest/performance/tests.py
langtest/robustness/__init__.py
langtest/utils/__init__.py
langsafe-0.1.dist-info/LICENSE
langsafe-0.1.dist-info/METADATA
langsafe-0.1.dist-info/WHEEL
langsafe-0.1.dist-info/top_level.txt
langsafe-0.1.dist-info/RECORD
