Metadata-Version: 2.1
Name: langsafe
Version: 0.1
Summary: An evaluation library for NLP models
Author: Openlayer
Author-email: engineers@openlayer.com
License-File: LICENSE
Requires-Dist: numpy
Requires-Dist: scipy
Requires-Dist: pandas
Requires-Dist: rouge-score
